[{"name":"zbxss","path":"/root/custom/zbxss/dist/zbxss_linux_386/zbxss","goos":"linux","goarch":"386","internal_type":4,"type":"Binary","extra":{"Binary":"zbxss","Ext":"","ID":"zbxss"}},{"name":"zbxss","path":"/root/custom/zbxss/dist/zbxss_linux_amd64_v1/zbxss","goos":"linux","goarch":"amd64","goamd64":"v1","internal_type":4,"type":"Binary","extra":{"Binary":"zbxss","Ext":"","ID":"zbxss"}},{"name":"zbxss","path":"/root/custom/zbxss/dist/zbxss_linux_arm64/zbxss","goos":"linux","goarch":"arm64","internal_type":4,"type":"Binary","extra":{"Binary":"zbxss","Ext":"","ID":"zbxss"}},{"name":"zbxss.exe","path":"/root/custom/zbxss/dist/zbxss_windows_amd64_v1/zbxss.exe","goos":"windows","goarch":"amd64","goamd64":"v1","internal_type":4,"type":"Binary","extra":{"Binary":"zbxss","Ext":".exe","ID":"zbxss"}},{"name":"zbxss.exe","path":"/root/custom/zbxss/dist/zbxss_windows_arm64/zbxss.exe","goos":"windows","goarch":"arm64","internal_type":4,"type":"Binary","extra":{"Binary":"zbxss","Ext":".exe","ID":"zbxss"}},{"name":"zbxss","path":"/root/custom/zbxss/dist/zbxss_darwin_amd64_v1/zbxss","goos":"darwin","goarch":"amd64","goamd64":"v1","internal_type":4,"type":"Binary","extra":{"Binary":"zbxss","Ext":"","ID":"zbxss"}},{"name":"zbxss.exe","path":"/root/custom/zbxss/dist/zbxss_windows_386/zbxss.exe","goos":"windows","goarch":"386","internal_type":4,"type":"Binary","extra":{"Binary":"zbxss","Ext":".exe","ID":"zbxss"}},{"name":"zbxss","path":"/root/custom/zbxss/dist/zbxss_darwin_arm64/zbxss","goos":"darwin","goarch":"arm64","internal_type":4,"type":"Binary","extra":{"Binary":"zbxss","Ext":"","ID":"zbxss"}},{"name":"zbxss_0.0.1-next_Linux_i386.tar.gz","path":"dist/zbxss_0.0.1-next_Linux_i386.tar.gz","goos":"linux","goarch":"386","internal_type":1,"type":"Archive","extra":{"Binaries":["zbxss"],"Builds":[{"name":"zbxss","path":"/root/custom/zbxss/dist/zbxss_linux_386/zbxss","goos":"linux","goarch":"386","internal_type":4,"type":"Binary","extra":{"Binary":"zbxss","Ext":"","ID":"zbxss"}}],"Format":"tar.gz","ID":"default","Replaces":null,"WrappedIn":""}},{"name":"zbxss_0.0.1-next_Linux_arm64.tar.gz","path":"dist/zbxss_0.0.1-next_Linux_arm64.tar.gz","goos":"linux","goarch":"arm64","internal_type":1,"type":"Archive","extra":{"Binaries":["zbxss"],"Builds":[{"name":"zbxss","path":"/root/custom/zbxss/dist/zbxss_linux_arm64/zbxss","goos":"linux","goarch":"arm64","internal_type":4,"type":"Binary","extra":{"Binary":"zbxss","Ext":"","ID":"zbxss"}}],"Format":"tar.gz","ID":"default","Replaces":null,"WrappedIn":""}},{"name":"zbxss_0.0.1-next_Darwin_arm64.tar.gz","path":"dist/zbxss_0.0.1-next_Darwin_arm64.tar.gz","goos":"darwin","goarch":"arm64","internal_type":1,"type":"Archive","extra":{"Binaries":["zbxss"],"Builds":[{"name":"zbxss","path":"/root/custom/zbxss/dist/zbxss_darwin_arm64/zbxss","goos":"darwin","goarch":"arm64","internal_type":4,"type":"Binary","extra":{"Binary":"zbxss","Ext":"","ID":"zbxss"}}],"Format":"tar.gz","ID":"default","Replaces":null,"WrappedIn":""}},{"name":"zbxss_0.0.1-next_Linux_x86_64.tar.gz","path":"dist/zbxss_0.0.1-next_Linux_x86_64.tar.gz","goos":"linux","goarch":"amd64","goamd64":"v1","internal_type":1,"type":"Archive","extra":{"Binaries":["zbxss"],"Builds":[{"name":"zbxss","path":"/root/custom/zbxss/dist/zbxss_linux_amd64_v1/zbxss","goos":"linux","goarch":"amd64","goamd64":"v1","internal_type":4,"type":"Binary","extra":{"Binary":"zbxss","Ext":"","ID":"zbxss"}}],"Format":"tar.gz","ID":"default","Replaces":null,"WrappedIn":""}},{"name":"zbxss_0.0.1-next_Windows_arm64.tar.gz","path":"dist/zbxss_0.0.1-next_Windows_arm64.tar.gz","goos":"windows","goarch":"arm64","internal_type":1,"type":"Archive","extra":{"Binaries":["zbxss.exe"],"Builds":[{"name":"zbxss.exe","path":"/root/custom/zbxss/dist/zbxss_windows_arm64/zbxss.exe","goos":"windows","goarch":"arm64","internal_type":4,"type":"Binary","extra":{"Binary":"zbxss","Ext":".exe","ID":"zbxss"}}],"Format":"tar.gz","ID":"default","Replaces":null,"WrappedIn":""}},{"name":"zbxss_0.0.1-next_Windows_i386.tar.gz","path":"dist/zbxss_0.0.1-next_Windows_i386.tar.gz","goos":"windows","goarch":"386","internal_type":1,"type":"Archive","extra":{"Binaries":["zbxss.exe"],"Builds":[{"name":"zbxss.exe","path":"/root/custom/zbxss/dist/zbxss_windows_386/zbxss.exe","goos":"windows","goarch":"386","internal_type":4,"type":"Binary","extra":{"Binary":"zbxss","Ext":".exe","ID":"zbxss"}}],"Format":"tar.gz","ID":"default","Replaces":null,"WrappedIn":""}},{"name":"zbxss_0.0.1-next_Windows_x86_64.tar.gz","path":"dist/zbxss_0.0.1-next_Windows_x86_64.tar.gz","goos":"windows","goarch":"amd64","goamd64":"v1","internal_type":1,"type":"Archive","extra":{"Binaries":["zbxss.exe"],"Builds":[{"name":"zbxss.exe","path":"/root/custom/zbxss/dist/zbxss_windows_amd64_v1/zbxss.exe","goos":"windows","goarch":"amd64","goamd64":"v1","internal_type":4,"type":"Binary","extra":{"Binary":"zbxss","Ext":".exe","ID":"zbxss"}}],"Format":"tar.gz","ID":"default","Replaces":null,"WrappedIn":""}},{"name":"zbxss_0.0.1-next_Darwin_x86_64.tar.gz","path":"dist/zbxss_0.0.1-next_Darwin_x86_64.tar.gz","goos":"darwin","goarch":"amd64","goamd64":"v1","internal_type":1,"type":"Archive","extra":{"Binaries":["zbxss"],"Builds":[{"name":"zbxss","path":"/root/custom/zbxss/dist/zbxss_darwin_amd64_v1/zbxss","goos":"darwin","goarch":"amd64","goamd64":"v1","internal_type":4,"type":"Binary","extra":{"Binary":"zbxss","Ext":"","ID":"zbxss"}}],"Format":"tar.gz","ID":"default","Replaces":null,"WrappedIn":""}},{"name":"checksums.txt","path":"dist/checksums.txt","internal_type":12,"type":"Checksum","extra":{}}]